textassert/__init__.py
textassert/ai.py
textassert/render.py
textassert/schema/project.py
textassert-0.2.1.dist-info/METADATA
textassert-0.2.1.dist-info/WHEEL
textassert-0.2.1.dist-info/entry_points.txt
textassert-0.2.1.dist-info/RECORD
