Metadata-Version: 2.4
Name: textassert
Version: 0.2.1
Summary: A tool to use LLMs to run a test suite against your texts
Author-email: Travior <30752199+Travior@users.noreply.github.com>
Requires-Python: >=3.12
Requires-Dist: click>=8.1.8
Requires-Dist: instructor>=1.7.8
Requires-Dist: openai>=1.70.0
Requires-Dist: pydantic>=2.10.6
Requires-Dist: rich>=13.9.4
